helloworld.py
helloworld_nagarjun_appleguy-0.0.1.dist-info/LICENSE.txt
helloworld_nagarjun_appleguy-0.0.1.dist-info/METADATA
helloworld_nagarjun_appleguy-0.0.1.dist-info/WHEEL
helloworld_nagarjun_appleguy-0.0.1.dist-info/top_level.txt
helloworld_nagarjun_appleguy-0.0.1.dist-info/RECORD
