Metadata-Version: 2.1
Name: helloworld-nagarjun-appleguy
Version: 0.0.1
Summary: Hello World Functionality
Home-page: UNKNOWN
Author: Nagarjun
Author-email: abc@gmail.com
License: UNKNOWN
Platform: UNKNOWN
